sabr/__init__.py
sabr/stats.py
tests/__init__.py
tests/sabr/__init__.py
tests/sabr/test_stats.py
sabr-2.0.dist-info/LICENSE
sabr-2.0.dist-info/METADATA
sabr-2.0.dist-info/WHEEL
sabr-2.0.dist-info/top_level.txt
sabr-2.0.dist-info/RECORD
